stream_processor/__init__.py
stream_processor/exceptions.py
stream_processor/schedulers.py
stream_processor/stream.py
stream_processor/tasks.py
tests/__init__.py
tests/test_handlers.py
tests/test_schedulers.py
tests/test_stream.py
tests/test_task.py
stream_processor-0.0.2.dist-info/METADATA
stream_processor-0.0.2.dist-info/WHEEL
stream_processor-0.0.2.dist-info/top_level.txt
stream_processor-0.0.2.dist-info/RECORD
